{
  "area_name": "Doddakammanahalli",
  "osm_id": 19883338,
  "osm_type": "relation",
  "place_type": "administrative",
  "amenity_count": 60,
  "amenities": [
    {
      "type": "node",
      "id": 2105154661,
      "lat": 12.8578959,
      "lon": 77.5891475,
      "tags": {
        "amenity": "restaurant",
        "cuisine": "indian",
        "indoor_seating": "yes",
        "name": "Kubera Biriyani Paradise",
        "outdoor_seating": "no",
        "wheelchair": "no"
      }
    },
    {
      "type": "node",
      "id": 4440769883,
      "lat": 12.8615976,
      "lon": 77.5999324,
      "tags": {
        "amenity": "hospital",
        "name": "Myo Medex - Ace Speciality Clinic"
      }
    },
    {
      "type": "node",
      "id": 4440825591,
      "lat": 12.8616662,
      "lon": 77.5998009,
      "tags": {
        "name": "Medplu",
        "operator": "Medplus",
        "shop": "medical_supply"
      }
    },
    {
      "type": "node",
      "id": 4440825592,
      "lat": 12.8616489,
      "lon": 77.599633,
      "tags": {
        "name": "Thirumala Medical Store",
        "operator": "Thirumala Medical Store",
        "shop": "medical_supply"
      }
    },
    {
      "type": "node",
      "id": 4440863088,
      "lat": 12.8617817,
      "lon": 77.5996423,
      "tags": {
        "amenity": "restaurant",
        "name": "Sri Sai Sagar"
      }
    },
    {
      "type": "node",
      "id": 4443656796,
      "lat": 12.8565752,
      "lon": 77.5889783,
      "tags": {
        "addr:city": "Banglore",
        "addr:housenumber": "5",
        "addr:postcode": "560001",
        "addr:street": "Gottigere Tank Bund Road",
        "amenity": "police",
        "name": "Hulimavu Traffic Police Station",
        "phone": "080 2294 3030",
        "website": "bangaloretrafficpolice.gov.in"
      }
    },
    {
      "type": "node",
      "id": 5402224045,
      "lat": 12.8651422,
      "lon": 77.5982894,
      "tags": {
        "shop": "hairdresser"
      }
    },
    {
      "type": "node",
      "id": 5402308132,
      "lat": 12.861015,
      "lon": 77.6047599,
      "tags": {
        "amenity": "cafe"
      }
    },
    {
      "type": "node",
      "id": 5402312924,
      "lat": 12.8615906,
      "lon": 77.6001468,
      "tags": {
        "amenity": "cafe"
      }
    },
    {
      "type": "node",
      "id": 6349192885,
      "lat": 12.8435532,
      "lon": 77.5850056,
      "tags": {
        "addr:place": "Nekarara Colony",
        "amenity": "school",
        "isced:level": "2",
        "name": "GMPS Nekarara Colony",
        "name:kn": "ಸರ್ಕಾರಿ ಹಿರಿಯ ಪ್ರಾಥಮಿಕ ಶಾಲೆ ನೇಕಾರರ ಕಾಲೋನಿ",
        "operator": "Department of Education",
        "school": "primary"
      }
    },
    {
      "type": "node",
      "id": 6422302288,
      "lat": 12.8450701,
      "lon": 77.5941913,
      "tags": {
        "addr:place": "Basavanapura",
        "amenity": "school",
        "isced:level": "3",
        "name": "GLPS Basavanapura",
        "name:kn": "ಸರ್ಕಾರಿ ಕಿರಿಯ ಪ್ರಾಥಮಿಕ ಶಾಲೆ ಬಸವನಪುರ",
        "operator": "Department of Education",
        "school": "Higher Primary"
      }
    },
    {
      "type": "node",
      "id": 6944283814,
      "lat": 12.8579673,
      "lon": 77.5892687,
      "tags": {
        "addr:district": "Bengaluru Urban",
        "addr:full": "#3, Gottigere, Bannerghatta Main Road,Near Gottigere Bus Stand",
        "addr:postcode": "560083",
        "addr:state": "Karnataka",
        "amenity": "hospital",
        "healthcare": "hospital",
        "name": "Vijayashree Hospitals",
        "name:kn": "ವಿಜಯಶ್ರೀ ಆಸ್ಪತ್ರೆಗಳು",
        "source": "OpenGovernmentData",
        "wheelchair": "yes"
      }
    },
    {
      "type": "node",
      "id": 6944507682,
      "lat": 12.8443653,
      "lon": 77.583809,
      "tags": {
        "addr:district": "Bengaluru Urban",
        "addr:full": "Weavers Colony Main Road, Bannerghatta Road",
        "addr:postcode": "560083",
        "addr:state": "Karnataka",
        "amenity": "hospital",
        "name": "Banashankari Hospital",
        "source": "OpenGovernmentData"
      }
    },
    {
      "type": "node",
      "id": 7179141561,
      "lat": 12.8538911,
      "lon": 77.5889038,
      "tags": {
        "addr:city": "Bangalore",
        "addr:street": "Bannerghatta Road",
        "amenity": "restaurant",
        "cuisine": "regional",
        "name": "Guru Greens Family Restaurant",
        "outdoor_seating": "yes"
      }
    },
    {
      "type": "node",
      "id": 10697710409,
      "lat": 12.8582964,
      "lon": 77.5896874,
      "tags": {
        "amenity": "college",
        "name": "Dr. Ramanah Manohar College of Law"
      }
    },
    {
      "type": "node",
      "id": 11124783672,
      "lat": 12.8453185,
      "lon": 77.5866616,
      "tags": {
        "access": "permissive",
        "amenity": "parking",
        "parking": "surface"
      }
    },
    {
      "type": "node",
      "id": 12260569981,
      "lat": 12.8630573,
      "lon": 77.5910135,
      "tags": {
        "amenity": "restaurant",
        "name": "Soofi Mandi"
      }
    },
    {
      "type": "node",
      "id": 12555764467,
      "lat": 12.8557982,
      "lon": 77.6003522,
      "tags": {
        "amenity": "place_of_worship",
        "religion": "hindu"
      }
    },
    {
      "type": "way",
      "id": 227098103,
      "center": {
        "lat": 12.8625201,
        "lon": 77.5996559
      },
      "tags": {
        "amenity": "place_of_worship",
        "name": "Maramma Temple",
        "name:kn": "ಮಾರಮ್ಮ ದೇವಸ್ಥಾನ",
        "religion": "hindu"
      }
    },
    {
      "type": "way",
      "id": 362880542,
      "center": {
        "lat": 12.8576648,
        "lon": 77.592483
      },
      "tags": {
        "access": "private",
        "leisure": "playground"
      }
    },
    {
      "type": "way",
      "id": 362882070,
      "center": {
        "lat": 12.8656488,
        "lon": 77.5943914
      },
      "tags": {
        "leisure": "playground",
        "name": "Play Area"
      }
    },
    {
      "type": "way",
      "id": 412939998,
      "center": {
        "lat": 12.8383501,
        "lon": 77.5912895
      },
      "tags": {
        "access": "permissive",
        "garden:type": "arboretum",
        "landuse": "forest",
        "leisure": "garden",
        "name": "Kalkere Arboretum",
        "natural": "wood",
        "operator": "Karnataka Forest Department"
      }
    },
    {
      "type": "way",
      "id": 1149959414,
      "center": {
        "lat": 12.8474387,
        "lon": 77.5890874
      },
      "tags": {
        "amenity": "school",
        "name": "Sherwood High School"
      }
    },
    {
      "type": "way",
      "id": 1149959416,
      "center": {
        "lat": 12.8426521,
        "lon": 77.5886058
      },
      "tags": {
        "amenity": "fuel",
        "brand": "Bharat Petroleum",
        "brand:wikidata": "Q854826",
        "compressed_air": "yes",
        "name": "Bharat Petroleum",
        "name:kn": "ಭಾರತ್ ಪೆಟ್ರೋಲಿಯಂ"
      }
    },
    {
      "type": "way",
      "id": 1178402472,
      "center": {
        "lat": 12.8507133,
        "lon": 77.5945794
      },
      "tags": {
        "amenity": "college",
        "name": "T John College"
      }
    },
    {
      "type": "way",
      "id": 1199400804,
      "center": {
        "lat": 12.846001,
        "lon": 77.5868715
      },
      "tags": {
        "leisure": "pitch",
        "sport": "basketball"
      }
    },
    {
      "type": "way",
      "id": 1199400813,
      "center": {
        "lat": 12.8549618,
        "lon": 77.5936226
      },
      "tags": {
        "leisure": "park"
      }
    },
    {
      "type": "way",
      "id": 1199400823,
      "center": {
        "lat": 12.8580471,
        "lon": 77.5992472
      },
      "tags": {
        "amenity": "place_of_worship",
        "religion": "hindu"
      }
    },
    {
      "type": "way",
      "id": 1199400828,
      "center": {
        "lat": 12.8588181,
        "lon": 77.6050428
      },
      "tags": {
        "amenity": "school",
        "name": "VIBGYOR High School"
      }
    },
    {
      "type": "way",
      "id": 1199410733,
      "center": {
        "lat": 12.8449482,
        "lon": 77.5874491
      },
      "tags": {
        "leisure": "park"
      }
    },
    {
      "type": "way",
      "id": 1199410737,
      "center": {
        "lat": 12.8455953,
        "lon": 77.5863196
      },
      "tags": {
        "leisure": "park"
      }
    },
    {
      "type": "way",
      "id": 1199410738,
      "center": {
        "lat": 12.8462506,
        "lon": 77.5874658
      },
      "tags": {
        "leisure": "park"
      }
    },
    {
      "type": "way",
      "id": 1199410758,
      "center": {
        "lat": 12.8526846,
        "lon": 77.60538
      },
      "tags": {
        "leisure": "park"
      }
    },
    {
      "type": "way",
      "id": 1199410761,
      "center": {
        "lat": 12.8519431,
        "lon": 77.6034576
      },
      "tags": {
        "leisure": "park"
      }
    },
    {
      "type": "way",
      "id": 1199410766,
      "center": {
        "lat": 12.8490868,
        "lon": 77.5973361
      },
      "tags": {
        "amenity": "social_facility",
        "name": "St. Joseph Elderly Home",
        "social_facility": "assisted_living",
        "social_facility:for": "senior"
      }
    },
    {
      "type": "way",
      "id": 1199410767,
      "center": {
        "lat": 12.8504622,
        "lon": 77.5973448
      },
      "tags": {
        "amenity": "school",
        "name": "St. Joseph Nivas Special School"
      }
    },
    {
      "type": "way",
      "id": 1308843403,
      "center": {
        "lat": 12.8586171,
        "lon": 77.5898715
      },
      "tags": {
        "leisure": "park"
      }
    },
    {
      "type": "way",
      "id": 1308843476,
      "center": {
        "lat": 12.8566513,
        "lon": 77.5910315
      },
      "tags": {
        "leisure": "sports_centre"
      }
    },
    {
      "type": "way",
      "id": 1308843539,
      "center": {
        "lat": 12.8575989,
        "lon": 77.5923535
      },
      "tags": {
        "access": "private",
        "amenity": "parking",
        "parking": "street_side"
      }
    },
    {
      "type": "way",
      "id": 1308843540,
      "center": {
        "lat": 12.8588298,
        "lon": 77.5925183
      },
      "tags": {
        "access": "private",
        "amenity": "parking",
        "parking": "street_side"
      }
    },
    {
      "type": "way",
      "id": 1356594012,
      "center": {
        "lat": 12.8472255,
        "lon": 77.5935622
      },
      "tags": {
        "amenity": "place_of_worship",
        "name": "St. Anthony's Church",
        "religion": "christian"
      }
    },
    {
      "type": "way",
      "id": 1356594013,
      "center": {
        "lat": 12.8546646,
        "lon": 77.6022761
      },
      "tags": {
        "leisure": "park"
      }
    },
    {
      "type": "way",
      "id": 1356594014,
      "center": {
        "lat": 12.8548764,
        "lon": 77.6019314
      },
      "tags": {
        "leisure": "park"
      }
    },
    {
      "type": "way",
      "id": 1356594015,
      "center": {
        "lat": 12.8550522,
        "lon": 77.6016096
      },
      "tags": {
        "leisure": "park"
      }
    },
    {
      "type": "way",
      "id": 1356594026,
      "center": {
        "lat": 12.8541978,
        "lon": 77.5978256
      },
      "tags": {
        "amenity": "school"
      }
    },
    {
      "type": "way",
      "id": 1356594043,
      "center": {
        "lat": 12.8547613,
        "lon": 77.5910899
      },
      "tags": {
        "amenity": "place_of_worship",
        "landuse": "religious",
        "name": "Burhani Masjid",
        "religion": "muslim"
      }
    },
    {
      "type": "way",
      "id": 1356594054,
      "center": {
        "lat": 12.8497843,
        "lon": 77.6003362
      },
      "tags": {
        "addr:place": "Chikkana Halli",
        "amenity": "school",
        "isced:level": "2",
        "name": "Saint Francis Xavier HPS Chikkana Halli",
        "name:kn": "ಸೆಂಟ್‌ ಫ್ರ ಕ್ಸೇವಿಯರ್ ಹಿರಿಯ ಪ್ರಾಥಮಿಕ ಶಾಲೆ ಚಿಕ್ಕಕಮ್ಮನ ಹಳ್ಳಿ",
        "operator": "Pvt. Aided",
        "school": "primary"
      }
    },
    {
      "type": "way",
      "id": 1356594056,
      "center": {
        "lat": 12.848352,
        "lon": 77.5992907
      },
      "tags": {
        "amenity": "school"
      }
    },
    {
      "type": "way",
      "id": 1356594057,
      "center": {
        "lat": 12.8491463,
        "lon": 77.600381
      },
      "tags": {
        "amenity": "place_of_worship",
        "religion": "christian"
      }
    },
    {
      "type": "way",
      "id": 1356597058,
      "center": {
        "lat": 12.8568683,
        "lon": 77.5895168
      },
      "tags": {
        "amenity": "college"
      }
    },
    {
      "type": "way",
      "id": 1356597061,
      "center": {
        "lat": 12.8602658,
        "lon": 77.6007124
      },
      "tags": {
        "leisure": "pitch",
        "sport": "tennis"
      }
    },
    {
      "type": "way",
      "id": 1391339680,
      "center": {
        "lat": 12.8652327,
        "lon": 77.5937956
      },
      "tags": {
        "access": "private",
        "leisure": "pitch",
        "name": "Purva Panorama Tennis Court",
        "sport": "tennis"
      }
    },
    {
      "type": "way",
      "id": 1391339681,
      "center": {
        "lat": 12.864941,
        "lon": 77.5936866
      },
      "tags": {
        "access": "private",
        "leisure": "park"
      }
    },
    {
      "type": "way",
      "id": 1391388042,
      "center": {
        "lat": 12.8658569,
        "lon": 77.5940169
      },
      "tags": {
        "leisure": "swimming_pool"
      }
    },
    {
      "type": "way",
      "id": 1392516525,
      "center": {
        "lat": 12.8664725,
        "lon": 77.5930839
      },
      "tags": {
        "amenity": "theatre",
        "theatre:type": "amphi"
      }
    },
    {
      "type": "way",
      "id": 1424059159,
      "center": {
        "lat": 12.8668364,
        "lon": 77.5953037
      },
      "tags": {
        "access": "private",
        "leisure": "swimming_pool"
      }
    },
    {
      "type": "way",
      "id": 1424063535,
      "center": {
        "lat": 12.8632531,
        "lon": 77.5911378
      },
      "tags": {
        "amenity": "fuel"
      }
    },
    {
      "type": "way",
      "id": 1428276575,
      "center": {
        "lat": 12.8609402,
        "lon": 77.5988516
      },
      "tags": {
        "access": "private",
        "leisure": "swimming_pool"
      }
    },
    {
      "type": "way",
      "id": 1428276576,
      "center": {
        "lat": 12.8606954,
        "lon": 77.5989096
      },
      "tags": {
        "leisure": "pitch",
        "sport": "tennis"
      }
    },
    {
      "type": "way",
      "id": 1432358339,
      "center": {
        "lat": 12.8397174,
        "lon": 77.5940275
      },
      "tags": {
        "addr:housenumber": "93/2",
        "addr:postcode": "560083",
        "addr:street": "Hommadevanahalli Village Begur Hobli, Bengaluru South, Taluk",
        "amenity": "school",
        "email": "communications.oisbg@orchids.edu.in",
        "name": "Orchids The International School - Yelahanka",
        "name:en": "Orchids The International School, Bannerghatta",
        "opening_hours": "Mo-Su 09:00-18:30",
        "operator": "Orchids International School",
        "phone": "9513731352",
        "website": "https://www.orchidsinternationalschool.com/bangalore-branches/bannerghatta/"
      }
    }
  ]
}